Metadata-Version: 2.1
Name: piece-table
Version: 0.0.3
Summary: A Python implementation of the piece table data structure
Home-page: https://github.com/saiguy3/piece_table
Author: Sai Atmakuri
Author-email: saiatmakuri@yahoo.com
License: MIT
Keywords: piecetable,table
Platform: UNKNOWN
Classifier: Development Status :: 1 - Planning
Classifier: License :: OSI Approved :: MIT License
Classifier: Intended Audience :: Developers
Classifier: Operating System :: OS Independent
Classifier: Programming Language :: Python :: 3
Classifier: Programming Language :: Python :: 3.6
Classifier: Programming Language :: Python :: 3.7
Classifier: Programming Language :: Python :: 3.8
Classifier: Topic :: Utilities
Requires-Python: >=3
